access_django_user_admin/__init__.py
access_django_user_admin/admin.py
access_django_user_admin/apps.py
access_django_user_admin/forms.py
access_django_user_admin/models.py
access_django_user_admin/urls.py
access_django_user_admin/utils.py
access_django_user_admin/views.py
access_django_user_admin/access_django_user_admin_api_service/__init__.py
access_django_user_admin/access_django_user_admin_api_service/djangouser.py
access_django_user_admin/static/__init__.py
access_django_user_admin/static/style-serviceindex.css
access_django_user_admin/static/access_django_user_admin/__init__.py
access_django_user_admin/static/access_django_user_admin/fonts/glyphicons-halflings-regular.eot
access_django_user_admin/static/access_django_user_admin/fonts/glyphicons-halflings-regular.svg
access_django_user_admin/static/access_django_user_admin/fonts/glyphicons-halflings-regular.ttf
access_django_user_admin/static/access_django_user_admin/fonts/glyphicons-halflings-regular.woff
access_django_user_admin/static/access_django_user_admin/img/ACCS050322_ACCESS_Brand_Operations-RGB.png
access_django_user_admin/static/access_django_user_admin/img/favicon.ico
access_django_user_admin/templates/__init__.py
access_django_user_admin/templates/access_django_user_admin/__init__.py
access_django_user_admin/templates/access_django_user_admin/access_django_user_admin.html
access_django_user_admin/templates/access_django_user_admin/add_user.html
access_django_user_admin/templates/access_django_user_admin/base_nav_none.html
access_django_user_admin/templates/access_django_user_admin/edit_user.html
access_django_user_admin/templates/access_django_user_admin/logout.html
access_django_user_admin/templates/access_django_user_admin/unprivileged.html
access_django_user_admin/templatetags/__init__.py
access_django_user_admin/templatetags/user_admin_tags.py
access_django_user_admin/templatetags/__pycache__/__init__.cpython-312.pyc
access_django_user_admin-1.5.3.dist-info/licenses/LICENSE
access_django_user_admin-1.5.3.dist-info/METADATA
access_django_user_admin-1.5.3.dist-info/WHEEL
access_django_user_admin-1.5.3.dist-info/top_level.txt
access_django_user_admin-1.5.3.dist-info/RECORD
