Metadata-Version: 2.4
Name: access_django_user_admin
Version: 1.5.3
Summary: Django User Admin for ACCESS Django Apps
Home-page: https://github.com/pypa/sampleproject
Author: Jesse Lambertson
Author-email: Jesse Lambertson <jelambe@iu.edu>
License-Expression: Apache-2.0
Project-URL: Homepage, https://github.com/access-ci-org/Operations_ACCESS_Django_User_Admin
Project-URL: Issues, https://github.com/access-ci-org/Operations_ACCESS_Django_User_Admin/issues
Classifier: Programming Language :: Python :: 3
Classifier: Operating System :: OS Independent
Requires-Python: >=3.7, <4
License-File: LICENSE
Dynamic: author
Dynamic: home-page
Dynamic: license-file
Dynamic: requires-python
